{
    "extensions": {
        "policies": [
            {
                "category": "composition",
                "implementation": "CompositionPolicy.js",
                "depends": [ "$injector" ],
                "message": "Objects of this type cannot contain objects of that type."
            },
            {
                "category": "composition",
                "implementation": "CompositionMutabilityPolicy.js",
                "message": "Objects of this type cannot be modified."
            },
            {
                "category": "composition",
                "implementation": "CompositionModelPolicy.js",
                "message": "Objects of this type cannot contain other objects."
            },
            {
                "category": "action",
                "implementation": "ComposeActionPolicy.js",
                "depends": [ "$injector" ],
                "message": "Objects of this type cannot contain objects of that type."
            }
        ]
    }
}